MANIFEST.in
README.md
setup.py
scripts/cfind
scripts/roscreate-shortcuts
scripts/yujin_init_workspace
scripts/yujin_platform
scripts/yujin_toolchain
src/yujin_tools/__init__.py
src/yujin_tools/init_workspace.py
src/yujin_tools.egg-info/PKG-INFO
src/yujin_tools.egg-info/SOURCES.txt
src/yujin_tools.egg-info/dependency_links.txt
src/yujin_tools.egg-info/top_level.txt